COPYRIGHT
LICENSE
MANIFEST.in
README.md
setup.cfg
setup.py
bin/gampc
bin/gampc-module
gampc/__init__.py
gampc/app.py
gampc/data.py
gampc.egg-info/PKG-INFO
gampc.egg-info/SOURCES.txt
gampc.egg-info/dependency_links.txt
gampc.egg-info/requires.txt
gampc.egg-info/top_level.txt
gampc/locale/messages.pot
gampc/locale/es/LC_MESSAGES/gampc.po
gampc/locale/fr/LC_MESSAGES/gampc.po
gampc/ui/current.ui
gampc/ui/window.ui
gampc/util/__init__.py
gampc/util/db.py
gampc/util/dialog.py
gampc/util/logger.py
gampc/util/module.py
gampc/util/recordlist.py
gampc/util/resource.py
gampc/util/ssde.py
gampc/util/unit.py
misc/begnac.gampc.desktop
misc/begnac.gampc.service
misc/gampc.1
misc/separator.mp3